twoSeparateGates/design.v
module and_area( 
  input wire in1,
  input wire in2,
  output wire out1_and
);
  
  assign out1_and = in1 & in2;
  // and(out1_and, in1, in2); 
endmodule

module gates_area(
  input wire in1,
  input wire in2,
  input wire in3,
  output wire out_or
);
  
  wire internal_wire;
  
  and_area A1(in1, in2, internal_wire);
  or(out_or, in3, internal_wire);
endmodule

twoSeparateGatesForLoop/testbench.v
module gates_area_tb();

  reg in1_tb = 1;
  reg in2_tb = 0;
  reg in3_tb = 0;
  wire out_tb;
  
  gates_area UUT1(
    .in1(in1_tb),
    .in2(in2_tb),
    .in3(in3_tb),
    .out_or(out_tb)
  );
  
  integer i = 0;

  initial begin
    $dumpfile("tb.vcd"); 
    $dumpvars;
    $display("\t\t time | in1 | in2 | in3 | out");
    
    for(i=0; i<=7; i=i+1)
      begin
        #1       
        in1_tb = 1^in1_tb;
        in2_tb = i>>1&1;
        in3_tb = i>>2&1;
        $monitor($time, "  |  %d  |  %d  |  %d  |  %d", in1_tb, in2_tb, in3_tb, out_tb);
      end
  end
      
endmodule

LearningVerilog/simpleProgrammableGate/modelSimSimulation/tb.vcd
$date
	Sun May  9 13:15:19 2021
$end
$version
	ModelSim Version 2020.1
$end
$timescale
	1ps
$end

$scope module gates_area_tb $end
$var reg 1 ! in1_tb $end
$var reg 1 " in2_tb $end
$var reg 1 # in3_tb $end
$var wire 1 $ out_tb $end
$var integer 32 % i $end

$scope module UUT1 $end
$var wire 1 & in1 $end
$var wire 1 ' in2 $end
$var wire 1 ( in3 $end
$var wire 1 $ out_or $end
$var wire 1 ) internal_wire $end

$scope module A1 $end
$var wire 1 & in1 $end
$var wire 1 ' in2 $end
$var wire 1 ) out1_and $end
$upscope $end
$upscope $end
$upscope $end
$enddefinitions $end
#0
$dumpvars
1!
0"
0#
b0 %
0$
0)
0(
0'
1&
$end
#1
0!
b1 %
0&
#2
1!
b10 %
1&
#3
0!
1"
b11 %
0&
1'
#4
1!
b100 %
1&
1)
1$
#5
0!
0"
1#
b101 %
0&
0'
1(
0)
#6
1!
b110 %
1&
#7
0!
1"
b111 %
0&
1'
#8
1!
b1000 %
1&
1)
