passAlaboratory/design.v
/* This code was created in order to pass the laboratory at my univeristy. We got datasheet ADS8588H device and
based on waveforms from this datasheet I wrote this code. ADS8588H is 16-bit ADC. */
`timescale 1ns/1ns // `timescale <unit of time>/<precision> 

module ADS8588H(
  input wire refsel,
  output reg busy,
  output wire rstdata,
  input wire stby,
  input wire convsta,
  input wire convstb,
  input wire reset,
  input wire range,
  input wire cs,
  input wire rd_sclk,
  input wire par_ser,
  inout wire [15:0] db, // inout - is bidirectional port
  output wire douta,
  output wire doutb,
  input wire [2:0] os
);

  wire internal_clock;				// freq divider, using for sampling freq 100 kHz clock
  reg[99:0] counter = 100'd0;		// freq divider, counter variable, for 100 kHz clock
  parameter DIVISOR = 100'd100;		// freq divider, prescale factor, for 100 kHz clock
  reg configuration_Flag = 1'b0; 	// 0 - any setup condition are not fulfill
  wire convstAB;					// in serial mode convstA/B should be connected, auxiliary variable
  reg start_timer = 1'b0;			// using in timer for busy signal
  reg[19:0] counter_for_busy = 20'd0;	// using in timer for busy signal
  reg rst_flag = 1'b0;
  reg[19:0] counter_for_reset = 20'd0;	// using in timer for busy signal

  and(convstAB, convsta, convstb); // It's gate level, gate_name(output,input,input);

  /* frequency divider, 100 kHz */
  always @(posedge rd_sclk)
    begin
      counter <= counter + 1; 	// increment counter
      if(counter >= (DIVISOR-1)) // if counter is equal prescale factor, reset counter
        counter <= 0;
    end
  // If we see "assign" it means, that it's register level
  // (condition) ? conditionFulfilled : conditionNotFulfilled ;
  assign clock_for_sampl = (counter<DIVISOR/2) ? 1'b0 : 1'b1;	// setting duty cycle, DIVISOR/2 means 50/50

  /* check setup conditions */
  always @(posedge rd_sclk)
    begin	// if conditions are set, change configuration_Flag
      if(refsel & stby & par_ser & db[15] & ~range & ~rst_flag & ~os[2:0]) 
        configuration_Flag = 1'b1;
      else configuration_Flag = 1'b0;
    end

  /* set timer for busy out, when conversion starts */
  always @(posedge convstAB) start_timer = (configuration_Flag) ? 1 : 0;
  // (condition) ? conditionFulfilled : conditionNotFulfilled ;

  /* when timer is on, set busy in high up to 1200 ns */
  always @(posedge rd_sclk)
    begin
      if(start_timer) 
        begin
          busy = 1;
          counter_for_busy <= counter_for_busy + 1;		// increment cnt
          if(counter_for_busy == 12) start_timer = 0; 	// count to 12, one clk is eq 100 ns, so 12 is eq 1200 ns
        end
      else 
        begin
          counter_for_busy = 0;	// if start_timer is off, reset cnt
          busy = 0;				// if start_timer is off, reset busy
        end
    end

  /* after falling edge on reset, set rst_flag */
  always @(negedge reset) rst_flag = 1;

  /* when rst_flag is on, run timer, when timer is overflow, reset rst_flag */
  always @(posedge rd_sclk)
    begin
      if(rst_flag)
        begin
          counter_for_reset <= counter_for_reset + 1;
          if(counter_for_reset == 8) rst_flag = 0;          
        end
      else counter_for_reset = 0;
    end

endmodule

LearningVerilog/passAlaboratory/testbench.v
/* This code was created in order to pass the laboratory at my univeristy. We got datasheet ADS8588H device and
based on waveforms from this datasheet I wrote this code. ADS8588H is 16-bit ADC. */
`timescale 1ns/1ns 	// `timescale <unit of time>/<precision> 

`define tPH_CN 2000	// CONVSTA/B duration high time pulse [ns]
`define tPL_CN 2000	// CONVSTA/B duration low time pulse [ns]
`define tSU_BSYCS 10	// time delay on CS after low edge on BUSY [ns]
`define tCONV 1240	// conversion time: BUSY high time, when oversampling is disabled [ns]
`define tD_CNBSY 10	// time delay on BUSY after high edge on CONVSTA/B [ns]
`define tPH_RST 1700// rst high time, min 10 ns

module ADS8588H_tb();

  reg sys_clk = 0;  // main clock 10 MHz 
  reg refsel_tb;  	// var for reference voltage. 1 - internal ref, 0 - external
  reg stby_tb;  	// 1 - standby mode, 0 - shut down device
  reg convsta_tb;	// conversion start A between 1-4 channels, 1 - start sampling and conv process
  reg convstb_tb;	// conversion start B between 5-8 channels
  reg reset_tb;		// 1 - reset device. Start reset on falling edge after high pulse 
  reg range_tb;		// control measurement range. 1 - 10 V, 0 - 5 V  
  reg cs_tb;		// can use more devs on the same buses 
  reg rd_sclk_tb;	// clock
  reg par_ser_tb;	
  wire [15:0] db_tb;
  /*For serial work:
  	db is duplex bus in serial mode:
    db[15] 	- logic 1 means parallel byte mode, 0 - serial mode 
    db[14] 	- tied to low
    db[13:9] - tied to low
    db[8] 	- output data for 5-8 channels
    db[7] 	- output data for 1-4 channels
    db[6:0] - tied to low
  */
  reg [2:0] os_tb;		// used for oversampling. 000 - oversamplig is disabled  
  reg db_bus_ctrl = 0;	// auxiliary var to control 15 register in db bus
  integer i;			// to control for loop

  and(db_tb[15], db_bus_ctrl, 1); // allow set device in serial mode (db_tb[15] = 1)

  ADS8588H UUT( // UUT is an instance of the gate module. UUT - unit under test
    .rd_sclk(sys_clk), // Binding vars from test with vars from model
    .refsel(refsel_tb),
    .stby(stby_tb),
    .par_ser(par_ser_tb),
    .db(db_tb),
    .range(range_tb),
    .reset(reset_tb),
    .os(os_tb),
    .convsta(convsta_tb),
    .convstb(convstb_tb)
  );

  initial begin // Behavioral level, there are two types of blocks at this level: initial and 
    // always. Inside these blocks, the instructions are executed sequentially.
    $dumpfile("tb.vcd"); // $dumpfile - should be given at the beginning to
    // monitor the state of the variables from beginning.
    $dumpvars;
    // set all vars to fulfill initial conditions, if is set 
    // configuration_Flag in our model should be = 1
    refsel_tb = 1;
    stby_tb = 1;
    par_ser_tb = 1;
    db_bus_ctrl <= 1;
    range_tb = 0;
    reset_tb = 0;
    os_tb[2:0] = 0'b000;
    #10  

    for(i = 0; i < 50; i = i+1)
      begin
        convsta_tb = 1;
        convstb_tb = 1;
        #(`tPH_CN)
        convsta_tb = 0;
        convstb_tb = 0;
        #(`tPL_CN);  
        if(i == 25 || i == 49)	// reset device
          begin
            reset_tb = 1;
            #(`tPH_RST)
            reset_tb = 0;
          end
      end

    #400000 $finish;
  end

  always #50 sys_clk <= ~sys_clk; // generate 20 MHz clock

endmodule

passAlaboratory/modelSimSimulation/tb.vcd
$date
	Sun May  9 12:58:34 2021
$end
$version
	ModelSim Version 2020.1
$end
$timescale
	1ns
$end

$scope module ADS8588H_tb $end
$var reg 1 ! sys_clk $end
$var reg 1 " refsel_tb $end
$var reg 1 # stby_tb $end
$var reg 1 $ convsta_tb $end
$var reg 1 % convstb_tb $end
$var reg 1 & reset_tb $end
$var reg 1 ' range_tb $end
$var reg 1 ( cs_tb $end
$var reg 1 ) rd_sclk_tb $end
$var reg 1 * par_ser_tb $end
$var wire 1 + db_tb [15] $end
$var wire 1 , db_tb [14] $end
$var wire 1 - db_tb [13] $end
$var wire 1 . db_tb [12] $end
$var wire 1 / db_tb [11] $end
$var wire 1 0 db_tb [10] $end
$var wire 1 1 db_tb [9] $end
$var wire 1 2 db_tb [8] $end
$var wire 1 3 db_tb [7] $end
$var wire 1 4 db_tb [6] $end
$var wire 1 5 db_tb [5] $end
$var wire 1 6 db_tb [4] $end
$var wire 1 7 db_tb [3] $end
$var wire 1 8 db_tb [2] $end
$var wire 1 9 db_tb [1] $end
$var wire 1 : db_tb [0] $end
$var reg 3 ; os_tb [2:0] $end
$var reg 1 < db_bus_ctrl $end
$var integer 32 = i $end

$scope module UUT $end
$var parameter 100 > DIVISOR $end
$var wire 1 ? refsel $end
$var reg 1 @ busy $end
$var wire 1 A rstdata $end
$var wire 1 B stby $end
$var wire 1 C convsta $end
$var wire 1 D convstb $end
$var wire 1 E reset $end
$var wire 1 F range $end
$var wire 1 G cs $end
$var wire 1 H rd_sclk $end
$var wire 1 I par_ser $end
$var wire 1 + db [15] $end
$var wire 1 , db [14] $end
$var wire 1 - db [13] $end
$var wire 1 . db [12] $end
$var wire 1 / db [11] $end
$var wire 1 0 db [10] $end
$var wire 1 1 db [9] $end
$var wire 1 2 db [8] $end
$var wire 1 3 db [7] $end
$var wire 1 4 db [6] $end
$var wire 1 5 db [5] $end
$var wire 1 6 db [4] $end
$var wire 1 7 db [3] $end
$var wire 1 8 db [2] $end
$var wire 1 9 db [1] $end
$var wire 1 : db [0] $end
$var wire 1 J douta $end
$var wire 1 K doutb $end
$var wire 1 L os [2] $end
$var wire 1 M os [1] $end
$var wire 1 N os [0] $end
$var wire 1 O internal_clock $end
$var reg 100 P counter [99:0] $end
$var reg 1 Q configuration_Flag $end
$var wire 1 R convstAB $end
$var reg 1 S start_timer $end
$var reg 20 T counter_for_busy [19:0] $end
$var reg 1 U rst_flag $end
$var reg 20 V counter_for_reset [19:0] $end
$var wire 1 W clock_for_sampl $end
$upscope $end
$upscope $end
$enddefinitions $end
#0
$dumpvars
0!
1"
1#
x$
x%
0&
0'
x(
x)
1*
b0 ;
1<
x@
b0 P
0Q
0S
b0 T
1U
b0 V
b1100100 >
bx =
z:
z9
z8
z7
z6
z5
z4
z3
z2
z1
z0
z/
z.
z-
z,
1+
zO
xR
0W
xD
xC
0N
0M
0L
0E
0F
1I
1B
1?
0H
zA
zG
zJ
zK
$end
#10
b0 =
1$
1%
1C
1D
1R
#50
1!
1H
0@
b1 P
b1 V
#100
0!
0H
#150
1!
1H
b10 P
b10 V
#200
0!
0H
#250
1!
1H
b11 P
b11 V
#300
0!
0H
#350
1!
1H
b100 P
b100 V
#400
0!
0H
#450
1!
1H
b101 P
b101 V
#500
0!
0H
#550
1!
1H
b110 P
b110 V
#600
0!
0H
#650
1!
1H
b111 P
b111 V
#700
0!
0H
#750
1!
1H
b1000 P
b1000 V
#800
0!
0H
#850
1!
1H
0U
b1001 P
b1001 V
#900
0!
0H
#950
1!
1H
1Q
b0 V
b1010 P
#1000
0!
0H
#1050
1!
1H
b1011 P
#1100
0!
0H
#1150
1!
1H
b1100 P
#1200
0!
0H
#1250
1!
1H
b1101 P
#1300
0!
0H
#1350
1!
1H
b1110 P
#1400
0!
0H
#1450
1!
1H
b1111 P
#1500
0!
0H
#1550
1!
1H
b10000 P
#1600
0!
0H
#1650
1!
1H
b10001 P
#1700
0!
0H
#1750
1!
1H
b10010 P
#1800
0!
0H
#1850
1!
1H
b10011 P
#1900
0!
0H
#1950
1!
1H
b10100 P
#2000
0!
0H
#2010
0$
0%
0C
0D
0R
#2050
1!
1H
b10101 P
#2100
0!
0H
#2150
1!
1H
b10110 P
#2200
0!
0H
#2250
1!
1H
b10111 P
#2300
0!
0H
#2350
1!
1H
b11000 P
#2400
0!
0H
#2450
1!
1H
b11001 P
#2500
0!
0H
#2550
1!
1H
b11010 P
#2600
0!
0H
#2650
1!
1H
b11011 P
#2700
0!
0H
#2750
1!
1H
b11100 P
#2800
0!
0H
#2850
1!
1H
b11101 P
#2900
0!
0H
#2950
1!
1H
b11110 P
#3000
0!
0H
#3050
1!
1H
b11111 P
#3100
0!
0H
#3150
1!
1H
b100000 P
#3200
0!
0H
#3250
1!
1H
b100001 P
#3300
0!
0H
#3350
1!
1H
b100010 P
#3400
0!
0H
#3450
1!
1H
b100011 P
#3500
0!
0H
#3550
1!
1H
b100100 P
#3600
0!
0H
#3650
1!
1H
b100101 P
#3700
0!
0H
#3750
1!
1H
b100110 P
#3800
0!
0H
#3850
1!
1H
b100111 P
#3900
0!
0H
#3950
1!
1H
b101000 P
#4000
0!
0H
#4010
b1 =
1$
1%
1C
1D
1R
1S
#4050
1!
1H
1@
b101001 P
b1 T
#4100
0!
0H
#4150
1!
1H
b101010 P
b10 T
#4200
0!
0H
#4250
1!
1H
b101011 P
b11 T
#4300
0!
0H
#4350
1!
1H
b101100 P
b100 T
#4400
0!
0H
#4450
1!
1H
b101101 P
b101 T
#4500
0!
0H
#4550
1!
1H
b101110 P
b110 T
#4600
0!
0H
#4650
1!
1H
b101111 P
b111 T
#4700
0!
0H
#4750
1!
1H
b110000 P
b1000 T
#4800
0!
0H
#4850
1!
1H
b110001 P
b1001 T
#4900
0!
0H
#4950
1!
1H
b110010 P
b1010 T
1W
#5000
0!
0H
#5050
1!
1H
b110011 P
b1011 T
#5100
0!
0H
#5150
1!
1H
b110100 P
b1100 T
#5200
0!
0H
#5250
1!
1H
0S
b110101 P
b1101 T
#5300
0!
0H
#5350
1!
1H
b0 T
0@
b110110 P
#5400
0!
0H
#5450
1!
1H
b110111 P
#5500
0!
0H
#5550
1!
1H
b111000 P
#5600
0!
0H
#5650
1!
1H
b111001 P
#5700
0!
0H
#5750
1!
1H
b111010 P
#5800
0!
0H
#5850
1!
1H
b111011 P
#5900
0!
0H
#5950
1!
1H
b111100 P
#6000
0!
0H
#6010
0$
0%
0C
0D
0R
#6050
1!
1H
b111101 P
#6100
0!
0H
#6150
1!
1H
b111110 P
#6200
0!
0H
#6250
1!
1H
b111111 P
#6300
0!
0H
#6350
1!
1H
b1000000 P
#6400
0!
0H
#6450
1!
1H
b1000001 P
#6500
0!
0H
#6550
1!
1H
b1000010 P
#6600
0!
0H
#6650
1!
1H
b1000011 P
#6700
0!
0H
#6750
1!
1H
b1000100 P
#6800
0!
0H
#6850
1!
1H
b1000101 P
#6900
0!
0H
#6950
1!
1H
b1000110 P
#7000
0!
0H
#7050
1!
1H
b1000111 P
#7100
0!
0H
#7150
1!
1H
b1001000 P
#7200
0!
0H
#7250
1!
1H
b1001001 P
#7300
0!
0H
#7350
1!
1H
b1001010 P
#7400
0!
0H
#7450
1!
1H
b1001011 P
#7500
0!
0H
#7550
1!
1H
b1001100 P
#7600
0!
0H
#7650
1!
1H
b1001101 P
#7700
0!
0H
#7750
1!
1H
b1001110 P
#7800
0!
0H
#7850
1!
1H
b1001111 P
#7900
0!
0H
#7950
1!
1H
b1010000 P
#8000
0!
0H
#8010
b10 =
1$
1%
1C
1D
1R
1S
#8050
1!
1H
1@
b1010001 P
b1 T
#8100
0!
0H
#8150
1!
1H
b1010010 P
b10 T
#8200
0!
0H
#8250
1!
1H
b1010011 P
b11 T
#8300
0!
0H
#8350
1!
1H
b1010100 P
b100 T
#8400
0!
0H
#8450
1!
1H
b1010101 P
b101 T
#8500
0!
0H
#8550
1!
1H
b1010110 P
b110 T
#8600
0!
0H
#8650
1!
1H
b1010111 P
b111 T
#8700
0!
0H
#8750
1!
1H
b1011000 P
b1000 T
#8800
0!
0H
#8850
1!
1H
b1011001 P
b1001 T
#8900
0!
0H
#8950
1!
1H
b1011010 P
b1010 T
#9000
0!
0H
#9050
1!
1H
b1011011 P
b1011 T
#9100
0!
0H
#9150
1!
1H
b1011100 P
b1100 T
#9200
0!
0H
#9250
1!
1H
0S
b1011101 P
b1101 T
#9300
0!
0H
#9350
1!
1H
b0 T
0@
b1011110 P
#9400
0!
0H
#9450
1!
1H
b1011111 P
#9500
0!
0H
#9550
1!
1H
b1100000 P
#9600
0!
0H
#9650
1!
1H
b1100001 P
#9700
0!
0H
#9750
1!
1H
b1100010 P
#9800
0!
0H
#9850
1!
1H
b1100011 P
#9900
0!
0H
#9950
1!
1H
b1100100 P
b0 P
0W
#10000
0!
0H
#10010
0$
0%
0C
0D
0R
#10050
1!
1H
b1 P
#10100
0!
0H
#10150
1!
1H
b10 P
#10200
0!
0H
#10250
1!
1H
b11 P
#10300
0!
0H
#10350
1!
1H
b100 P
#10400
0!
0H
#10450
1!
1H
b101 P
#10500
0!
0H
#10550
1!
1H
b110 P
#10600
0!
0H
#10650
1!
1H
b111 P
#10700
0!
0H
#10750
1!
1H
b1000 P
#10800
0!
0H
#10850
1!
1H
b1001 P
#10900
0!
0H
#10950
1!
1H
b1010 P
#11000
0!
0H
#11050
1!
1H
b1011 P
#11100
0!
0H
#11150
1!
1H
b1100 P
#11200
0!
0H
#11250
1!
1H
b1101 P
#11300
0!
0H
#11350
1!
1H
b1110 P
#11400
0!
0H
#11450
1!
1H
b1111 P
#11500
0!
0H
#11550
1!
1H
b10000 P
#11600
0!
0H
#11650
1!
1H
b10001 P
#11700
0!
0H
#11750
1!
1H
b10010 P
#11800
0!
0H
#11850
1!
1H
b10011 P
#11900
0!
0H
#11950
1!
1H
b10100 P
#12000
0!
0H
#12010
b11 =
1$
1%
1C
1D
1R
1S
#12050
1!
1H
1@
b10101 P
b1 T
#12100
0!
0H
#12150
1!
1H
b10110 P
b10 T
#12200
0!
0H
#12250
1!
1H
b10111 P
b11 T
#12300
0!
0H
#12350
1!
1H
b11000 P
b100 T
#12400
0!
0H
#12450
1!
1H
b11001 P
b101 T
#12500
0!
0H
#12550
1!
1H
b11010 P
b110 T
#12600
0!
0H
#12650
1!
1H
b11011 P
b111 T
#12700
0!
0H
#12750
1!
1H
b11100 P
b1000 T
#12800
0!
0H
#12850
1!
1H
b11101 P
b1001 T
#12900
0!
0H
#12950
1!
1H
b11110 P
b1010 T
#13000
0!
0H
#13050
1!
1H
b11111 P
b1011 T
#13100
0!
0H
#13150
1!
1H
b100000 P
b1100 T
#13200
0!
0H
#13250
1!
1H
0S
b100001 P
b1101 T
#13300
0!
0H
#13350
1!
1H
b0 T
0@
b100010 P
#13400
0!
0H
#13450
1!
1H
b100011 P
#13500
0!
0H
#13550
1!
1H
b100100 P
#13600
0!
0H
#13650
1!
1H
b100101 P
#13700
0!
0H
#13750
1!
1H
b100110 P
#13800
0!
0H
#13850
1!
1H
b100111 P
#13900
0!
0H
#13950
1!
1H
b101000 P
#14000
0!
0H
#14010
0$
0%
0C
0D
0R
#14050
1!
1H
b101001 P
#14100
0!
0H
#14150
1!
1H
b101010 P
#14200
0!
0H
#14250
1!
1H
b101011 P
#14300
0!
0H
#14350
1!
1H
b101100 P
#14400
0!
0H
#14450
1!
1H
b101101 P
#14500
0!
0H
#14550
1!
1H
b101110 P
#14600
0!
0H
#14650
1!
1H
b101111 P
#14700
0!
0H
#14750
1!
1H
b110000 P
#14800
0!
0H
#14850
1!
1H
b110001 P
#14900
0!
0H
#14950
1!
1H
b110010 P
1W
#15000
0!
0H
#15050
1!
1H
b110011 P
#15100
0!
0H
#15150
1!
1H
b110100 P
#15200
0!
0H
#15250
1!
1H
b110101 P
#15300
0!
0H
#15350
1!
1H
b110110 P
#15400
0!
0H
#15450
1!
1H
b110111 P
#15500
0!
0H
#15550
1!
1H
b111000 P
#15600
0!
0H
#15650
1!
1H
b111001 P
#15700
0!
0H
#15750
1!
1H
b111010 P
#15800
0!
0H
#15850
1!
1H
b111011 P
#15900
0!
0H
#15950
1!
1H
b111100 P
#16000
0!
0H
#16010
b100 =
1$
1%
1C
1D
1R
1S
#16050
1!
1H
1@
b111101 P
b1 T
#16100
0!
0H
#16150
1!
1H
b111110 P
b10 T
#16200
0!
0H
#16250
1!
1H
b111111 P
b11 T
#16300
0!
0H
#16350
1!
1H
b1000000 P
b100 T
#16400
0!
0H
#16450
1!
1H
b1000001 P
b101 T
#16500
0!
0H
#16550
1!
1H
b1000010 P
b110 T
#16600
0!
0H
#16650
1!
1H
b1000011 P
b111 T
#16700
0!
0H
#16750
1!
1H
b1000100 P
b1000 T
#16800
0!
0H
#16850
1!
1H
b1000101 P
b1001 T
#16900
0!
0H
#16950
1!
1H
b1000110 P
b1010 T
#17000
0!
0H
#17050
1!
1H
b1000111 P
b1011 T
#17100
0!
0H
#17150
1!
1H
b1001000 P
b1100 T
#17200
0!
0H
#17250
1!
1H
0S
b1001001 P
b1101 T
#17300
0!
0H
#17350
1!
1H
b0 T
0@
b1001010 P
#17400
0!
0H
#17450
1!
1H
b1001011 P
#17500
0!
0H
#17550
1!
1H
b1001100 P
#17600
0!
0H
#17650
1!
1H
b1001101 P
#17700
0!
0H
#17750
1!
1H
b1001110 P
#17800
0!
0H
#17850
1!
1H
b1001111 P
#17900
0!
0H
#17950
1!
1H
b1010000 P
#18000
0!
0H
#18010
0$
0%
0C
0D
0R
#18050
1!
1H
b1010001 P
#18100
0!
0H
#18150
1!
1H
b1010010 P
#18200
0!
0H
#18250
1!
1H
b1010011 P
#18300
0!
0H
#18350
1!
1H
b1010100 P
#18400
0!
0H
#18450
1!
1H
b1010101 P
#18500
0!
0H
#18550
1!
1H
b1010110 P
#18600
0!
0H
#18650
1!
1H
b1010111 P
#18700
0!
0H
#18750
1!
1H
b1011000 P
#18800
0!
0H
#18850
1!
1H
b1011001 P
#18900
0!
0H
#18950
1!
1H
b1011010 P
#19000
0!
0H
#19050
1!
1H
b1011011 P
#19100
0!
0H
#19150
1!
1H
b1011100 P
#19200
0!
0H
#19250
1!
1H
b1011101 P
#19300
0!
0H
#19350
1!
1H
b1011110 P
#19400
0!
0H
#19450
1!
1H
b1011111 P
#19500
0!
0H
#19550
1!
1H
b1100000 P
#19600
0!
0H
#19650
1!
1H
b1100001 P
#19700
0!
0H
#19750
1!
1H
b1100010 P
#19800
0!
0H
#19850
1!
1H
b1100011 P
#19900
0!
0H
#19950
1!
1H
b1100100 P
b0 P
0W
#20000
0!
0H
#20010
b101 =
1$
1%
1C
1D
1R
1S
#20050
1!
1H
1@
b1 P
b1 T
#20100
0!
0H
#20150
1!
1H
b10 P
b10 T
#20200
0!
0H
#20250
1!
1H
b11 P
b11 T
#20300
0!
0H
#20350
1!
1H
b100 P
b100 T
#20400
0!
0H
#20450
1!
1H
b101 P
b101 T
#20500
0!
0H
#20550
1!
1H
b110 P
b110 T
#20600
0!
0H
#20650
1!
1H
b111 P
b111 T
#20700
0!
0H
#20750
1!
1H
b1000 P
b1000 T
#20800
0!
0H
#20850
1!
1H
b1001 P
b1001 T
#20900
0!
0H
#20950
1!
1H
b1010 P
b1010 T
#21000
0!
0H
#21050
1!
1H
b1011 P
b1011 T
#21100
0!
0H
#21150
1!
1H
b1100 P
b1100 T
#21200
0!
0H
#21250
1!
1H
0S
b1101 P
b1101 T
#21300
0!
0H
#21350
1!
1H
b0 T
0@
b1110 P
#21400
0!
0H
#21450
1!
1H
b1111 P
#21500
0!
0H
#21550
1!
1H
b10000 P
#21600
0!
0H
#21650
1!
1H
b10001 P
#21700
0!
0H
#21750
1!
1H
b10010 P
#21800
0!
0H
#21850
1!
1H
b10011 P
#21900
0!
0H
#21950
1!
1H
b10100 P
#22000
0!
0H
#22010
0$
0%
0C
0D
0R
#22050
1!
1H
b10101 P
#22100
0!
0H
#22150
1!
1H
b10110 P
#22200
0!
0H
#22250
1!
1H
b10111 P
#22300
0!
0H
#22350
1!
1H
b11000 P
#22400
0!
0H
#22450
1!
1H
b11001 P
#22500
0!
0H
#22550
1!
1H
b11010 P
#22600
0!
0H
#22650
1!
1H
b11011 P
#22700
0!
0H
#22750
1!
1H
b11100 P
#22800
0!
0H
#22850
1!
1H
b11101 P
#22900
0!
0H
#22950
1!
1H
b11110 P
#23000
0!
0H
#23050
1!
1H
b11111 P
#23100
0!
0H
#23150
1!
1H
b100000 P
#23200
0!
0H
#23250
1!
1H
b100001 P
#23300
0!
0H
#23350
1!
1H
b100010 P
#23400
0!
0H
#23450
1!
1H
b100011 P
#23500
0!
0H
#23550
1!
1H
b100100 P
#23600
0!
0H
#23650
1!
1H
b100101 P
#23700
0!
0H
#23750
1!
1H
b100110 P
#23800
0!
0H
#23850
1!
1H
b100111 P
#23900
0!
0H
#23950
1!
1H
b101000 P
#24000
0!
0H
#24010
b110 =
1$
1%
1C
1D
1R
1S
#24050
1!
1H
1@
b101001 P
b1 T
#24100
0!
0H
#24150
1!
1H
b101010 P
b10 T
#24200
0!
0H
#24250
1!
1H
b101011 P
b11 T
#24300
0!
0H
#24350
1!
1H
b101100 P
b100 T
#24400
0!
0H
#24450
1!
1H
b101101 P
b101 T
#24500
0!
0H
#24550
1!
1H
b101110 P
b110 T
#24600
0!
0H
#24650
1!
1H
b101111 P
b111 T
#24700
0!
0H
#24750
1!
1H
b110000 P
b1000 T
#24800
0!
0H
#24850
1!
1H
b110001 P
b1001 T
#24900
0!
0H
#24950
1!
1H
b110010 P
b1010 T
1W
#25000
0!
0H
#25050
1!
1H
b110011 P
b1011 T
#25100
0!
0H
#25150
1!
1H
b110100 P
b1100 T
#25200
0!
0H
#25250
1!
1H
0S
b110101 P
b1101 T
#25300
0!
0H
#25350
1!
1H
b0 T
0@
b110110 P
#25400
0!
0H
#25450
1!
1H
b110111 P
#25500
0!
0H
#25550
1!
1H
b111000 P
#25600
0!
0H
#25650
1!
1H
b111001 P
#25700
0!
0H
#25750
1!
1H
b111010 P
#25800
0!
0H
#25850
1!
1H
b111011 P
#25900
0!
0H
#25950
1!
1H
b111100 P
#26000
0!
0H
#26010
0$
0%
0C
0D
0R
#26050
1!
1H
b111101 P
#26100
0!
0H
#26150
1!
1H
b111110 P
#26200
0!
0H
#26250
1!
1H
b111111 P
#26300
0!
0H
#26350
1!
1H
b1000000 P
#26400
0!
0H
#26450
1!
1H
b1000001 P
#26500
0!
0H
#26550
1!
1H
b1000010 P
#26600
0!
0H
#26650
1!
1H
b1000011 P
#26700
0!
0H
#26750
1!
1H
b1000100 P
#26800
0!
0H
#26850
1!
1H
b1000101 P
#26900
0!
0H
#26950
1!
1H
b1000110 P
#27000
0!
0H
#27050
1!
1H
b1000111 P
#27100
0!
0H
#27150
1!
1H
b1001000 P
#27200
0!
0H
#27250
1!
1H
b1001001 P
#27300
0!
0H
#27350
1!
1H
b1001010 P
#27400
0!
0H
#27450
1!
1H
b1001011 P
#27500
0!
0H
#27550
1!
1H
b1001100 P
#27600
0!
0H
#27650
1!
1H
b1001101 P
#27700
0!
0H
#27750
1!
1H
b1001110 P
#27800
0!
0H
#27850
1!
1H
b1001111 P
#27900
0!
0H
#27950
1!
1H
b1010000 P
#28000
0!
0H
#28010
b111 =
1$
1%
1C
1D
1R
1S
#28050
1!
1H
1@
b1010001 P
b1 T
#28100
0!
0H
#28150
1!
1H
b1010010 P
b10 T
#28200
0!
0H
#28250
1!
1H
b1010011 P
b11 T
#28300
0!
0H
#28350
1!
1H
b1010100 P
b100 T
#28400
0!
0H
#28450
1!
1H
b1010101 P
b101 T
#28500
0!
0H
#28550
1!
1H
b1010110 P
b110 T
#28600
0!
0H
#28650
1!
1H
b1010111 P
b111 T
#28700
0!
0H
#28750
1!
1H
b1011000 P
b1000 T
#28800
0!
0H
#28850
1!
1H
b1011001 P
b1001 T
#28900
0!
0H
#28950
1!
1H
b1011010 P
b1010 T
#29000
0!
0H
#29050
1!
1H
b1011011 P
b1011 T
#29100
0!
0H
#29150
1!
1H
b1011100 P
b1100 T
#29200
0!
0H
#29250
1!
1H
0S
b1011101 P
b1101 T
#29300
0!
0H
#29350
1!
1H
b0 T
0@
b1011110 P
#29400
0!
0H
#29450
1!
1H
b1011111 P
#29500
0!
0H
#29550
1!
1H
b1100000 P
#29600
0!
0H
#29650
1!
1H
b1100001 P
#29700
0!
0H
#29750
1!
1H
b1100010 P
#29800
0!
0H
#29850
1!
1H
b1100011 P
#29900
0!
0H
#29950
1!
1H
b1100100 P
b0 P
0W
#30000
0!
0H
#30010
0$
0%
0C
0D
0R
#30050
1!
1H
b1 P
#30100
0!
0H
#30150
1!
1H
b10 P
#30200
0!
0H
#30250
1!
1H
b11 P
#30300
0!
0H
#30350
1!
1H
b100 P
#30400
0!
0H
#30450
1!
1H
b101 P
#30500
0!
0H
#30550
1!
1H
b110 P
#30600
0!
0H
#30650
1!
1H
b111 P
#30700
0!
0H
#30750
1!
1H
b1000 P
#30800
0!
0H
#30850
1!
1H
b1001 P
#30900
0!
0H
#30950
1!
1H
b1010 P
#31000
0!
0H
#31050
1!
1H
b1011 P
#31100
0!
0H
#31150
1!
1H
b1100 P
#31200
0!
0H
#31250
1!
1H
b1101 P
#31300
0!
0H
#31350
1!
1H
b1110 P
#31400
0!
0H
#31450
1!
1H
b1111 P
#31500
0!
0H
#31550
1!
1H
b10000 P
#31600
0!
0H
#31650
1!
1H
b10001 P
#31700
0!
0H
#31750
1!
1H
b10010 P
#31800
0!
0H
#31850
1!
1H
b10011 P
#31900
0!
0H
#31950
1!
1H
b10100 P
#32000
0!
0H
#32010
b1000 =
1$
1%
1C
1D
1R
1S
#32050
1!
1H
1@
b10101 P
b1 T
#32100
0!
0H
#32150
1!
1H
b10110 P
b10 T
#32200
0!
0H
#32250
1!
1H
b10111 P
b11 T
#32300
0!
0H
#32350
1!
1H
b11000 P
b100 T
#32400
0!
0H
#32450
1!
1H
b11001 P
b101 T
#32500
0!
0H
#32550
1!
1H
b11010 P
b110 T
#32600
0!
0H
#32650
1!
1H
b11011 P
b111 T
#32700
0!
0H
#32750
1!
1H
b11100 P
b1000 T
#32800
0!
0H
#32850
1!
1H
b11101 P
b1001 T
#32900
0!
0H
#32950
1!
1H
b11110 P
b1010 T
#33000
0!
0H
#33050
1!
1H
b11111 P
b1011 T
#33100
0!
0H
#33150
1!
1H
b100000 P
b1100 T
#33200
0!
0H
#33250
1!
1H
0S
b100001 P
b1101 T
#33300
0!
0H
#33350
1!
1H
b0 T
0@
b100010 P
#33400
0!
0H
#33450
1!
1H
b100011 P
#33500
0!
0H
#33550
1!
1H
b100100 P
#33600
0!
0H
#33650
1!
1H
b100101 P
#33700
0!
0H
#33750
1!
1H
b100110 P
#33800
0!
0H
#33850
1!
1H
b100111 P
#33900
0!
0H
#33950
1!
1H
b101000 P
#34000
0!
0H
#34010
0$
0%
0C
0D
0R
#34050
1!
1H
b101001 P
#34100
0!
0H
#34150
1!
1H
b101010 P
#34200
0!
0H
#34250
1!
1H
b101011 P
#34300
0!
0H
#34350
1!
1H
b101100 P
#34400
0!
0H
#34450
1!
1H
b101101 P
#34500
0!
0H
#34550
1!
1H
b101110 P
#34600
0!
0H
#34650
1!
1H
b101111 P
#34700
0!
0H
#34750
1!
1H
b110000 P
#34800
0!
0H
#34850
1!
1H
b110001 P
#34900
0!
0H
#34950
1!
1H
b110010 P
1W
#35000
0!
0H
#35050
1!
1H
b110011 P
#35100
0!
0H
#35150
1!
1H
b110100 P
#35200
0!
0H
#35250
1!
1H
b110101 P
#35300
0!
0H
#35350
1!
1H
b110110 P
#35400
0!
0H
#35450
1!
1H
b110111 P
#35500
0!
0H
#35550
1!
1H
b111000 P
#35600
0!
0H
